datalake/__init__.py
datalake/annotations.py
datalake/credentials.py
datalake/data_request.py
datalake/dataset.py
datalake/limits.py
datalake/searcher.py
datalake/settings.py
datalake/utils.py
datalake/__pycache__/__init__.cpython-37.pyc
datalake/__pycache__/annotations.cpython-37.pyc
datalake/__pycache__/credentials.cpython-37.pyc
datalake/__pycache__/data_request.cpython-37.pyc
datalake/__pycache__/dataset.cpython-37.pyc
datalake/__pycache__/limits.cpython-37.pyc
datalake/__pycache__/searcher.cpython-37.pyc
datalake/__pycache__/settings.cpython-37.pyc
datalake/__pycache__/utils.cpython-37.pyc
datalake/export/__init__.py
datalake/integrations/__init__.py
datalake/integrations/cvat.py
datalake/integrations/gdrive.py
datalake/integrations/label_studio.py
datalake/integrations/segmentation_masks.py
piedatalake-1.0.18.data/scripts/datalaker
piedatalake-1.0.18.dist-info/METADATA
piedatalake-1.0.18.dist-info/WHEEL
piedatalake-1.0.18.dist-info/top_level.txt
piedatalake-1.0.18.dist-info/zip-safe
piedatalake-1.0.18.dist-info/RECORD
