Metadata-Version: 2.1
Name: piedatalake
Version: 1.0.18
Summary: Datalake search engine
Home-page: https://github.com/PieDataLabs/datalake
Author: George Kasparyants
Author-email: gg@piedata.ai
License: UNKNOWN
Platform: macOS-10.16-x86_64-i386-64bit
Classifier: Intended Audience :: Developers
Classifier: Operating System :: OS Independent
Classifier: Topic :: Software Development :: Libraries :: Python Modules
Classifier: Programming Language :: Python
Classifier: Programming Language :: Python :: 3 :: Only
Classifier: Programming Language :: Python :: 3.6
Requires-Python: >=3.6
Requires-Dist: Pillow
Requires-Dist: numpy
Requires-Dist: scikit-image
Requires-Dist: parse
Requires-Dist: opencv-contrib-python
Requires-Dist: imantics
Requires-Dist: requests
Requires-Dist: tqdm
